AnkurKnapsack/__init__.py
AnkurKnapsack/knapsack.py
AnkurKnapsack-1.0.dist-info/METADATA
AnkurKnapsack-1.0.dist-info/WHEEL
AnkurKnapsack-1.0.dist-info/top_level.txt
AnkurKnapsack-1.0.dist-info/RECORD
